seplot/README.md
seplot/__init__.py
seplot/grapher.py
seplot/kw_dictionaries.py
seplot/seplot.py
seplot/seploter.py
seplot/style_dictionaries.py
seplot/styler.py
seplot-2.2.6.data/scripts/seplot
seplot-2.2.6.data/scripts/seploter.py
seplot-2.2.6.dist-info/LICENCE.md
seplot-2.2.6.dist-info/METADATA
seplot-2.2.6.dist-info/WHEEL
seplot-2.2.6.dist-info/top_level.txt
seplot-2.2.6.dist-info/RECORD
