Metadata-Version: 2.1
Name: seplot
Version: 2.2.6
Summary: A front-end for Python PyX
Home-page: https://github.com/SergeDmi/Python-Tools/
Author: Serge Dmitrieff
License: UNKNOWN
Platform: UNKNOWN
Requires-Dist: pyx
Requires-Dist: numpy
Requires-Dist: sio-tools
Requires-Dist: pandas
